amora/__init__.py
amora/cli/__init__.py
amora/cli/__main__.py
amora/cli/dash.py
amora/cli/feature_store.py
amora/cli/models.py
amora/cli/shared_options.py
amora/cli/type_specs.py
amora/cli/typer_app.py
amora/compilation.py
amora/config.py
amora/contracts.py
amora/dag.py
amora/dash/__init__.py
amora/dash/app.py
amora/dash/authentication.py
amora/dash/components/__init__.py
amora/dash/components/animation.py
amora/dash/components/dependency_dag.py
amora/dash/components/filters/__init__.py
amora/dash/components/filters/accepted_values_filter.py
amora/dash/components/filters/date_filter.py
amora/dash/components/filters/filter.py
amora/dash/components/materialization_badge.py
amora/dash/components/materialization_type_badge.py
amora/dash/components/model_code.py
amora/dash/components/model_columns.py
amora/dash/components/model_data_owner.py
amora/dash/components/model_datatable.py
amora/dash/components/model_details.py
amora/dash/components/model_labels.py
amora/dash/components/model_summary.py
amora/dash/components/model_viz.py
amora/dash/components/question_details.py
amora/dash/components/side_bar.py
amora/dash/components/user_avatar.py
amora/dash/config.py
amora/dash/css_styles.py
amora/dash/gunicorn/__init__.py
amora/dash/gunicorn/application.py
amora/dash/gunicorn/config.py
amora/dash/metrics.py
amora/dash/pages/__init__.py
amora/dash/pages/dashboard.py
amora/dash/pages/environment.py
amora/dash/pages/feature_store.py
amora/dash/pages/home.py
amora/dash/pages/models.py
amora/dash/pages/not_found_404.py
amora/dash/pages/owners.py
amora/dash/pages/questions.py
amora/dashboards.py
amora/feature_store/__init__.py
amora/feature_store/config.py
amora/feature_store/decorators.py
amora/feature_store/feature_view.py
amora/feature_store/logging.py
amora/feature_store/online_store.py
amora/feature_store/protocols.py
amora/feature_store/registry.py
amora/feature_store/type_mapping.py
amora/feature_store/usage_tracking.py
amora/logger.py
amora/manifest.py
amora-0.1.23.dist-info/LICENSE
amora-0.1.23.dist-info/METADATA
amora-0.1.23.dist-info/WHEEL
amora-0.1.23.dist-info/entry_points.txt
amora-0.1.23.dist-info/RECORD
