Metadata-Version: 2.1
Name: amora
Version: 0.1.23
Summary: Amora Data Build Tool
License: MIT
Author: diogommartins
Author-email: diogo.martins@stone.com.br
Requires-Python: >=3.8,<3.11
Classifier: Development Status :: 2 - Pre-Alpha
Classifier: License :: OSI Approved :: MIT License
Classifier: Operating System :: MacOS :: MacOS X
Classifier: Operating System :: POSIX :: Linux
Classifier: Programming Language :: Python :: 3
Classifier: Programming Language :: Python :: 3.8
Classifier: Programming Language :: Python :: 3.9
Classifier: Programming Language :: Python :: 3.10
Classifier: Programming Language :: SQL
Provides-Extra: dash
Provides-Extra: feature-store
Requires-Dist: Authlib (>=1.0) ; extra == "dash"
Requires-Dist: Jinja2 (>=3.0.3,<4.0.0)
Requires-Dist: SQLAlchemy[mypy] (>=1.4,<2.0)
Requires-Dist: Werkzeug (==2.2.3) ; extra == "dash"
Requires-Dist: dash-ace (>=0.2.1,<0.3.0) ; extra == "dash"
Requires-Dist: dash-bootstrap-components (>=1.4.1,<2.0.0) ; extra == "dash"
Requires-Dist: dash-cytoscape (==0.3.0) ; extra == "dash"
Requires-Dist: dash-extensions (>=0.1.10,<0.2.0) ; extra == "dash"
Requires-Dist: dash-mantine-components (>=0.10.2,<0.12.0) ; extra == "dash"
Requires-Dist: dash[testing] (==2.9.3) ; extra == "dash"
Requires-Dist: feast[gcp,redis] (==0.31.1) ; extra == "feature-store"
Requires-Dist: fsspec (>=2022.5.0,<2023.0.0)
Requires-Dist: gcsfs (>=2022.5.0,<2023.0.0)
Requires-Dist: gunicorn (>=20.1.0,<21.0.0) ; extra == "dash"
Requires-Dist: humanize (>=4.2.3,<5.0.0)
Requires-Dist: matplotlib (>=3.4.2,<4.0.0)
Requires-Dist: networkx[all] (>=2.6.3,<4.0.0)
Requires-Dist: pandas[output-formatting] (>=1.3.0,<2.0.0)
Requires-Dist: prometheus-fastapi-instrumentator (>=6.0.0,<7.0.0) ; extra == "feature-store"
Requires-Dist: prometheus-flask-exporter (==0.22.3) ; extra == "dash"
Requires-Dist: protobuf (>3,<5)
Requires-Dist: pydantic[email] (>=1.10.2,<2.0.0)
Requires-Dist: pytest (>=6.2.5,<8.0.0)
Requires-Dist: pytest-xdist[psutil] (>=2.5,<4.0)
Requires-Dist: rich (>=10.13,<13.0)
Requires-Dist: shed (>=0.9.5,<2023.6.0)
Requires-Dist: sqlalchemy-bigquery (>=1.4,<2.0)
Requires-Dist: sqlparse (>=0.3.1,<0.5.0)
Requires-Dist: typer[all] (>=0.4,<0.10)
